{"0": {"20": {"weight": 204}, "42": {"weight": 253}}, "1": {"20": {"weight": 318}, "25": {"weight": 297}, "19": {"weight": 55}}, "2": {"6": {"weight": 264}, "29": {"weight": 177}, "38": {"weight": 211}}, "3": {"47": {"weight": 23}}, "4": {"24": {"weight": 17}, "28": {"weight": 152}, "44": {"weight": 163}, "18": {"weight": 251}}, "5": {"43": {"weight": 330}, "24": {"weight": 248}, "16": {"weight": 628}, "48": {"weight": 204}, "27": {"weight": 182}}, "6": {"2": {"weight": 264}, "7": {"weight": 614}, "9": {"weight": 706}, "40": {"weight": 685}, "36": {"weight": 512}}, "7": {"6": {"weight": 614}, "8": {"weight": 305}}, "8": {"7": {"weight": 305}, "15": {"weight": 453}}, "9": {"6": {"weight": 706}, "13": {"weight": 115}, "18": {"weight": 96}, "40": {"weight": 183}, "36": {"weight": 354}}, "10": {"16": {"weight": 783}, "12": {"weight": 167}, "15": {"weight": 293}}, "11": {"14": {"weight": 114}, "12": {"weight": 122}, "16": {"weight": 539}}, "12": {"10": {"weight": 167}, "11": {"weight": 122}, "15": {"weight": 137}}, "13": {"9": {"weight": 115}, "14": {"weight": 105}}, "14": {"11": {"weight": 114}, "13": {"weight": 105}, "15": {"weight": 315}}, "15": {"8": {"weight": 453}, "10": {"weight": 293}, "12": {"weight": 137}, "14": {"weight": 315}}, "16": {"5": {"weight": 628}, "10": {"weight": 783}, "11": {"weight": 539}, "48": {"weight": 505}, "24": {"weight": 381}}, "17": {"21": {"weight": 139}, "22": {"weight": 391}, "45": {"weight": 394}, "30": {"weight": 422}}, "18": {"4": {"weight": 251}, "9": {"weight": 96}, "44": {"weight": 148}, "40": {"weight": 113}}, "19": {"1": {"weight": 55}, "25": {"weight": 288}}, "20": {"0": {"weight": 204}, "1": {"weight": 318}}, "21": {"17": {"weight": 139}, "42": {"weight": 284}, "23": {"weight": 107}}, "22": {"17": {"weight": 391}, "45": {"weight": 347}}, "23": {"21": {"weight": 107}, "29": {"weight": 392}, "37": {"weight": 354}}, "24": {"4": {"weight": 17}, "5": {"weight": 248}, "16": {"weight": 381}, "48": {"weight": 303}}, "25": {"1": {"weight": 297}, "19": {"weight": 288}, "26": {"weight": 211}, "43": {"weight": 326}}, "26": {"25": {"weight": 211}, "43": {"weight": 302}, "28": {"weight": 245}}, "27": {"5": {"weight": 182}, "47": {"weight": 190}, "48": {"weight": 191}}, "28": {"4": {"weight": 152}, "26": {"weight": 245}, "42": {"weight": 363}, "44": {"weight": 274}}, "29": {"2": {"weight": 177}, "23": {"weight": 392}, "38": {"weight": 112}, "45": {"weight": 354}, "37": {"weight": 109}}, "30": {"17": {"weight": 422}, "45": {"weight": 406}, "46": {"weight": 218}, "35": {"weight": 395}}, "31": {"35": {"weight": 200}, "32": {"weight": 130}, "34": {"weight": 288}}, "32": {"31": {"weight": 130}, "33": {"weight": 47}, "35": {"weight": 206}}, "33": {"32": {"weight": 47}, "34": {"weight": 475}}, "34": {"31": {"weight": 288}, "33": {"weight": 475}, "35": {"weight": 488}}, "35": {"30": {"weight": 395}, "31": {"weight": 200}, "32": {"weight": 206}, "34": {"weight": 488}, "46": {"weight": 266}}, "36": {"6": {"weight": 512}, "9": {"weight": 354}, "37": {"weight": 165}, "39": {"weight": 410}, "44": {"weight": 560}, "40": {"weight": 303}}, "37": {"23": {"weight": 354}, "29": {"weight": 109}, "36": {"weight": 165}}, "38": {"2": {"weight": 211}, "29": {"weight": 112}, "46": {"weight": 432}, "45": {"weight": 319}}, "39": {"36": {"weight": 410}, "41": {"weight": 123}, "44": {"weight": 304}, "40": {"weight": 299}}, "40": {"6": {"weight": 685}, "9": {"weight": 183}, "18": {"weight": 113}, "36": {"weight": 303}, "39": {"weight": 299}, "46": {"weight": 701}}, "41": {"39": {"weight": 123}, "42": {"weight": 145}}, "42": {"0": {"weight": 253}, "21": {"weight": 284}, "28": {"weight": 363}, "41": {"weight": 145}}, "43": {"5": {"weight": 330}, "25": {"weight": 326}, "26": {"weight": 302}}, "44": {"4": {"weight": 163}, "18": {"weight": 148}, "28": {"weight": 274}, "36": {"weight": 560}, "39": {"weight": 304}}, "45": {"17": {"weight": 394}, "22": {"weight": 347}, "29": {"weight": 354}, "30": {"weight": 406}, "38": {"weight": 319}, "46": {"weight": 247}}, "46": {"30": {"weight": 218}, "35": {"weight": 266}, "38": {"weight": 432}, "45": {"weight": 247}, "40": {"weight": 701}}, "47": {"3": {"weight": 23}, "27": {"weight": 190}}, "48": {"5": {"weight": 204}, "16": {"weight": 505}, "24": {"weight": 303}, "27": {"weight": 191}}}